gym_distractions/__init__.py
gym_distractions/distractors/__init__.py
gym_distractions/distractors/background_source.py
gym_distractions/distractors/dots/__init__.py
gym_distractions/distractors/dots/constant_dots.py
gym_distractions/distractors/dots/dots_source.py
gym_distractions/distractors/dots/episode_dots.py
gym_distractions/distractors/dots/linear_dots.py
gym_distractions/distractors/dots/pendulum_dots.py
gym_distractions/distractors/dots/quadlink_dots.py
gym_distractions/distractors/dots/random_dots.py
gym_distractions/distractors/noise.py
gym_distractions/distractors/random_color.py
gym_distractions/distractors/video_data_source.py
gym_distractions/errors.py
gym_distractions/merge_strategy/__init__.py
gym_distractions/type_mappings.py
gym_distractions/wrapper.py
gym_distractions/wrappers.py
gym_distractions-0.1.1.dist-info/WHEEL
gym_distractions-0.1.1.dist-info/METADATA
gym_distractions-0.1.1.dist-info/RECORD
