Metadata-Version: 2.1
Name: gym-distractions
Version: 0.1.1
Summary: Environment with different disk dynamics for distractions in RL environments
License: MIT
Author-email: Sebastian Markgraf <Sebastian-Markgraf@t-online.de>
Requires-Python: >=3.8
Requires-Dist: dm_control>=1.0.0
Requires-Dist: gymnasium>=0.27.0
Requires-Dist: imageio
Requires-Dist: n-link-simulator>=0.1.1
Requires-Dist: numpy
Requires-Dist: opencv-python
Requires-Dist: pytube
Requires-Dist: scikit-video
Provides-Extra: dev
Requires-Dist: pytest; extra == "dev"
Requires-Dist: pre-commit; extra == "dev"
Requires-Dist: pytest-cov; extra == "dev"
Requires-Dist: pyinstrument; extra == "dev"
Requires-Dist: black; extra == "dev"
Requires-Dist: ruff>=0.0.254; extra == "dev"
Provides-Extra: docs
Requires-Dist: sphinx>=6.1.3; extra == "docs"
Requires-Dist: sphinx-autodoc-typehints>=1.22; extra == "docs"
Requires-Dist: sphinxcontrib-apidoc>=0.3.0; extra == "docs"
